physicell_config/__init__.py
physicell_config/config_builder_modular.py
physicell_config/xml_loader.py
physicell_config/config/__init__.py
physicell_config/config/embedded_defaults.py
physicell_config/config/embedded_signals_behaviors.py
physicell_config/modules/__init__.py
physicell_config/modules/base.py
physicell_config/modules/cell_rules.py
physicell_config/modules/cell_rules_csv.py
physicell_config/modules/cell_types.py
physicell_config/modules/config_loader.py
physicell_config/modules/domain.py
physicell_config/modules/initial_conditions.py
physicell_config/modules/options.py
physicell_config/modules/physiboss.py
physicell_config/modules/save_options.py
physicell_config/modules/substrates.py
physicell_settings-0.4.5.dist-info/licenses/LICENSE
physicell_settings-0.4.5.dist-info/METADATA
physicell_settings-0.4.5.dist-info/WHEEL
physicell_settings-0.4.5.dist-info/entry_points.txt
physicell_settings-0.4.5.dist-info/top_level.txt
physicell_settings-0.4.5.dist-info/RECORD
