Metadata-Version: 2.4
Name: physicell-settings
Version: 0.4.5
Summary: User-friendly Python package for generating PhysiCell_settings.xml configuration files
Home-page: https://github.com/mruscone/PhysiCell_Settings
Author: Marco Ruscone
Author-email: ym.ruscone94@gmail.com
Project-URL: Bug Tracker, https://github.com/mruscone/PhysiCell_Settings/issues
Project-URL: Documentation, https://github.com/mruscone/PhysiCell_Settings#readme
Project-URL: Source Code, https://github.com/mruscone/PhysiCell_Settings
Keywords: physicell,multicellular,simulation,biology,computational-biology,bioinformatics,cancer,tissue,xml,configuration
Classifier: Development Status :: 4 - Beta
Classifier: Intended Audience :: Science/Research
Classifier: Topic :: Scientific/Engineering :: Bio-Informatics
Classifier: License :: OSI Approved :: GNU General Public License v3 (GPLv3)
Classifier: Programming Language :: Python :: 3
Classifier: Programming Language :: Python :: 3.8
Classifier: Programming Language :: Python :: 3.9
Classifier: Programming Language :: Python :: 3.10
Classifier: Programming Language :: Python :: 3.11
Classifier: Programming Language :: Python :: 3.12
Classifier: Operating System :: OS Independent
Requires-Python: >=3.8
License-File: LICENSE
Provides-Extra: dev
Requires-Dist: pytest>=6.0; extra == "dev"
Requires-Dist: pytest-cov; extra == "dev"
Requires-Dist: black; extra == "dev"
Requires-Dist: flake8; extra == "dev"
Requires-Dist: mypy; extra == "dev"
Provides-Extra: docs
Requires-Dist: sphinx>=4.0; extra == "docs"
Requires-Dist: sphinx-rtd-theme; extra == "docs"
Requires-Dist: myst-parser; extra == "docs"
Dynamic: author
Dynamic: author-email
Dynamic: classifier
Dynamic: description
Dynamic: description-content-type
Dynamic: home-page
Dynamic: keywords
Dynamic: license-file
Dynamic: project-url
Dynamic: provides-extra
Dynamic: requires-python
Dynamic: summary
